miml/__init__.py
miml/classifier/__init__.py
miml/classifier/miml_classifier.py
miml/classifier/mi/__init__.py
miml/classifier/mi/apr_classifier.py
miml/classifier/mi/mi_wrapper_classifier.py
miml/classifier/mimlTOmi/__init__.py
miml/classifier/mimlTOmi/miml_to_mi_br_classifier.py
miml/classifier/mimlTOmi/miml_to_mi_classifier.py
miml/classifier/mimlTOmi/miml_to_mi_lp_classifier.py
miml/classifier/mimlTOml/__init__.py
miml/classifier/mimlTOml/miml_to_ml_classifier.py
miml/data/__init__.py
miml/data/bag.py
miml/data/dataset_utils.py
miml/data/instance.py
miml/data/miml_dataset.py
miml/datasets/miml_birds.arff
miml/datasets/miml_birds.csv
miml/datasets/miml_birds_random_20test.arff
miml/datasets/miml_birds_random_80train.arff
miml/datasets/toy.arff
miml/report/__init__.py
miml/report/report.py
miml/transformation/__init__.py
miml/transformation/mimlTOmi/__init__.py
miml/transformation/mimlTOmi/binary_relevance_transformation.py
miml/transformation/mimlTOmi/label_powerset_transformation.py
miml/transformation/mimlTOml/__init__.py
miml/transformation/mimlTOml/arithmetic.py
miml/transformation/mimlTOml/geometric.py
miml/transformation/mimlTOml/miml_to_ml_transformation.py
miml/transformation/mimlTOml/minmax.py
miml/tutorial/classifiers_comparison_experiment_miml.ipynb
miml/tutorial/classifiers_mimltomi.ipynb
miml/tutorial/classifiers_mimltoml.ipynb
miml/tutorial/data_miml.ipynb
miml/tutorial/train_test_experiment_miml.ipynb
miml/tutorial/transformations_miml.ipynb
mimllearning-1.0.11.dist-info/METADATA
mimllearning-1.0.11.dist-info/WHEEL
mimllearning-1.0.11.dist-info/licenses/LICENSE.txt
mimllearning-1.0.11.dist-info/RECORD
