Metadata-Version: 2.3
Name: mimllearning
Version: 1.0.11
Summary: MIML Learning Library
Project-URL: Homepage, https://github.com/p82maavd/miml
Author-email: Damian Martinez <damianmartinezavila@gmail.com>
License-Expression: GPL-3.0
License-File: LICENSE.txt
Keywords: data-science,machine-learning,miml,multi-instance,multilabel,python
Classifier: License :: OSI Approved :: GNU General Public License v3 or later (GPLv3+)
Classifier: Operating System :: OS Independent
Classifier: Programming Language :: Python :: 3
Requires-Python: >=3.8
